upscale_ncnn_py-1.3.0.dist-info/METADATA
upscale_ncnn_py-1.3.0.dist-info/WHEEL
upscale_ncnn_py-1.3.0.dist-info/entry_points.txt
upscale_ncnn_py-1.3.0.dist-info/licenses/LICENSE
upscale_ncnn_py/__init__.py
upscale_ncnn_py/upscale_ncnn_vulkan.py
upscale_ncnn_py/upscale_ncnn_vulkan_wrapper.cpython-312-x86_64-linux-gnu.so
upscale_ncnn_py/vcomp140.dll
upscale_ncnn_py-1.3.0.dist-info/RECORD
