Metadata-Version: 2.1
Name: upscale-ncnn-py
Version: 1.3.0
Author: TNTWise
Author-Email: Tohrusky <65994850+Tohrusky@users.noreply.github.com>, NevermindNilas <nilascontact@gmail.com>
License: BSD-3-Clause
Classifier: Programming Language :: Python :: 3.8
Classifier: Programming Language :: Python :: 3.9
Classifier: Programming Language :: Python :: 3.10
Classifier: Programming Language :: Python :: 3.11
Classifier: Programming Language :: Python :: 3.12
Classifier: Programming Language :: Python :: 3.13
Classifier: Programming Language :: C++
Project-URL: Homepage, https://github.com/NevermindNilas/upscale-ncnn-python-attempt
Project-URL: Repository, https://github.com/NevermindNilas/upscale-ncnn-python-attempt
Requires-Python: >=3.9
Requires-Dist: opencv-python
Requires-Dist: pillow
